mmseg_ext/__init__.py
mmseg_ext/version.py
mmseg_ext/apis/__init__.py
mmseg_ext/apis/common.py
mmseg_ext/apis/edge/__init__.py
mmseg_ext/apis/edge/inference.py
mmseg_ext/apis/edge/test.py
mmseg_ext/apis/edge/train.py
mmseg_ext/apis/seg/__init__.py
mmseg_ext/apis/seg/inference.py
mmseg_ext/apis/seg/test.py
mmseg_ext/apis/seg/train.py
mmseg_ext/core/__init__.py
mmseg_ext/core/eval_hooks.py
mmseg_ext/core/metrics.py
mmseg_ext/datasets/__init__.py
mmseg_ext/datasets/base_edge_dataset.py
mmseg_ext/datasets/base_seg_dataset.py
mmseg_ext/datasets/builder.py
mmseg_ext/datasets/custom_binary_edge_dataset.py
mmseg_ext/datasets/custom_multilabel_edge_dataset.py
mmseg_ext/datasets/custom_seg_dataset.py
mmseg_ext/datasets/pipelines/__init__.py
mmseg_ext/datasets/pipelines/compose.py
mmseg_ext/datasets/pipelines/formatting.py
mmseg_ext/datasets/pipelines/loading.py
mmseg_ext/datasets/pipelines/transforms.py
mmseg_ext/models/__init__.py
mmseg_ext/models/builder.py
mmseg_ext/models/backbones/__init__.py
mmseg_ext/models/backbones/resnet.py
mmseg_ext/models/detectors/__init__.py
mmseg_ext/models/detectors/base.py
mmseg_ext/models/detectors/basic_detector.py
mmseg_ext/models/edge_heads/__init__.py
mmseg_ext/models/edge_heads/casenet_head.py
mmseg_ext/models/edge_heads/multi_supervision_head.py
mmseg_ext/models/losses/__init__.py
mmseg_ext/models/losses/accuracy.py
mmseg_ext/models/losses/binary_edge_loss.py
mmseg_ext/models/losses/cross_entropy_loss.py
mmseg_ext/models/losses/dual_task_loss.py
mmseg_ext/models/losses/multilabel_edge_loss.py
mmseg_ext/models/losses/old_losses.py
mmseg_ext/models/losses/utils.py
mmseg_ext/models/necks/__init__.py
mmseg_ext/models/seg_heads/__init__.py
mmseg_ext/models/seg_heads/binary_hed_head.py
mmseg_ext/models/seg_heads/gscnn_head.py
mmseg_ext/models/seg_heads/manyedge_decode_head.py
mmseg_ext/models/seg_heads/mhjsb_deeplabv3plus.py
mmseg_ext/models/seg_heads/multitask_decode_head.py
mmseg_ext/models/segmentors/__init__.py
mmseg_ext-0.0.2.dist-info/LICENSE
mmseg_ext-0.0.2.dist-info/METADATA
mmseg_ext-0.0.2.dist-info/WHEEL
mmseg_ext-0.0.2.dist-info/top_level.txt
mmseg_ext-0.0.2.dist-info/RECORD
