Metadata-Version: 2.1
Name: mmseg-ext
Version: 0.0.2
Summary: Extended function for mmsegmentation
Home-page: http://github.com/haruishi43/mmseg_ext
Author: Haruya Ishikawa
Author-email: 
License: GNU General Public License 3.0
Keywords: computer vision,semantic segmentation,edge detection
Classifier: Development Status :: 4 - Beta
Classifier: Operating System :: OS Independent
Classifier: Programming Language :: Python :: 3.7
Classifier: Programming Language :: Python :: 3.8
Classifier: Programming Language :: Python :: 3.9
License-File: LICENSE
Requires-Dist: matplotlib
Requires-Dist: scikit-learn
Requires-Dist: scikit-image
Requires-Dist: prettytable
Requires-Dist: cityscapesscripts
Requires-Dist: mmsegmentation (==0.27.0)
Requires-Dist: pyEdgeEval (>=0.2.0)
